MANIFEST.in
README.md
setup.cfg
setup.py
superset/__init__.py
superset/cache_util.py
superset/cli.py
superset/config.py
superset/dataframe.py
superset/db_engine_specs.py
superset/extract_table_names.py
superset/import_util.py
superset/jinja_context.py
superset/legacy.py
superset/security.py
superset/sql_lab.py
superset/sql_parse.py
superset/stats_logger.py
superset/utils.py
superset/viz.py
superset/bin/__init__.py
superset/bin/superset
superset/connectors/__init__.py
superset/connectors/connector_registry.py
superset/connectors/base/__init__.py
superset/connectors/base/models.py
superset/connectors/base/views.py
superset/connectors/druid/__init__.py
superset/connectors/druid/models.py
superset/connectors/druid/views.py
superset/connectors/sqla/__init__.py
superset/connectors/sqla/models.py
superset/connectors/sqla/views.py
superset/data/__init__.py
superset/data/birth_france_data_for_country_map.csv
superset/data/birth_names.json.gz
superset/data/countries.json.gz
superset/data/countries.md
superset/data/countries.py
superset/data/energy.json.gz
superset/data/multiformat_time_series.json.gz
superset/data/random_time_series.json.gz
superset/data/san_francisco.csv.gz
superset/data/unicode_utf8_unixnl_test.csv
superset/data/__pycache__/__init__.cpython-35.pyc
superset/data/__pycache__/countries.cpython-35.pyc
superset/db_engines/__init__.py
superset/db_engines/hive.py
superset/db_engines/presto.py
superset/hand/__init__.py
superset/hand/interceptor.py
superset/hand/mail.py
superset/hand/models.py
superset/hand/role_manager.py
superset/hand/role_views.py
superset/hand/scheduler.py
superset/hand/start.py
superset/hand/views.py
superset/hand/viz.py
superset/migrations/README
superset/migrations/__init__.py
superset/migrations/alembic.ini
superset/migrations/env.py
superset/migrations/script.py.mako
superset/migrations/__pycache__/env.cpython-35.pyc
superset/migrations/versions/1226819ee0e3_fix_wrong_constraint_on_table_columns.py
superset_hand_china.egg-info/PKG-INFO
superset_hand_china.egg-info/SOURCES.txt
superset_hand_china.egg-info/dependency_links.txt
superset_hand_china.egg-info/not-zip-safe
superset_hand_china.egg-info/requires.txt
superset_hand_china.egg-info/top_level.txt