Metadata-Version: 1.1
Name: superset-hand-china
Version: 1.3.8
Summary: A interactive data visualization platform build on SqlAlchemy and druid.io
Home-page: https://rdc.hand-china.com/gitlab/rdc_report/superset18
Author: ujhujuh
Author-email: 643240108@qq.com
License: Apache License, Version 2.0
Download-URL: https://rdc.hand-china.com/gitlab/rdc_report/superset18
Platform: UNKNOWN
Classifier: Programming Language :: Python :: 2.7
Classifier: Programming Language :: Python :: 3.4
Classifier: Programming Language :: Python :: 3.5
